.gitignore
.gitmodules
CMakeLists.txt
format.sh
setup.py
_skbuild/linux-x86_64-3.8/cmake-install/python/cloud_geodesic/_cloud_geodesic.cpython-38-x86_64-linux-gnu.so
example/demo.py
example/main.cpp
matplotplusplus/.clang-format
matplotplusplus/.gitignore
matplotplusplus/CMakeLists.txt
matplotplusplus/CMakePresets.json
matplotplusplus/LICENSE
matplotplusplus/Matplot++Config.cmake.in
matplotplusplus/README.md
matplotplusplus/examples.md
matplotplusplus/gallery.md
matplotplusplus/index.md
matplotplusplus/mkdocs.yml
matplotplusplus/.github/FUNDING.yml
matplotplusplus/.github/ISSUE_TEMPLATE/bug-report.md
matplotplusplus/.github/ISSUE_TEMPLATE/config.yml
matplotplusplus/.github/ISSUE_TEMPLATE/feature-request.md
matplotplusplus/.github/workflows/build.yml
matplotplusplus/.github/workflows/docs.yml
matplotplusplus/.github/workflows/label.yml
matplotplusplus/.github/workflows/mind-your-language.yml
matplotplusplus/cmake/FindFFTW.cmake
matplotplusplus/cmake/FindFilesystem.cmake
matplotplusplus/cmake/FindGLAD.cmake
matplotplusplus/cmake/FindOpenCV.cmake
matplotplusplus/cmake/functions.cmake
matplotplusplus/cmake/functions/link_external_libraries.cmake
matplotplusplus/cmake/functions/project_flags.cmake
matplotplusplus/cmake/functions/sanitizers.cmake
matplotplusplus/cmake/functions/target_options.cmake
matplotplusplus/docs/.gitignore
matplotplusplus/docs/COMPLETE_GALLERY.md
matplotplusplus/docs/white-paper.md
matplotplusplus/docs/examples/annotations/arrow/arrow_1.svg
matplotplusplus/docs/examples/annotations/arrow/arrow_1_thumb.png
matplotplusplus/docs/examples/annotations/arrow/arrow_2.svg
matplotplusplus/docs/examples/annotations/arrow/arrow_2_thumb.png
matplotplusplus/docs/examples/annotations/ellipse/ellipse_1.svg
matplotplusplus/docs/examples/annotations/ellipse/ellipse_1_thumb.png
matplotplusplus/docs/examples/annotations/fill/fill_1.svg
matplotplusplus/docs/examples/annotations/fill/fill_1_thumb.png
matplotplusplus/docs/examples/annotations/line/line_1.svg
python/cloud_geodesic.egg-info/PKG-INFO
python/cloud_geodesic.egg-info/SOURCES.txt
python/cloud_geodesic.egg-info/dependency_links.txt
python/cloud_geodesic.egg-info/requires.txt
python/cloud_geodesic.egg-info/top_level.txt
