Metadata-Version: 2.1
Name: cloud-geodesic
Version: 0.0.1
Summary: python interface to cloud geodesic
Author: Hirokazu Ishida
License: MIT
